zigcc/__init__.py
zigcc-1.0.1.dist-info/METADATA
zigcc-1.0.1.dist-info/WHEEL
zigcc-1.0.1.dist-info/entry_points.txt
zigcc-1.0.1.dist-info/licenses/LICENSE
zigcc-1.0.1.dist-info/RECORD
