Metadata-Version: 2.3
Name: zigcc
Version: 1.0.1
Summary: Util scripts aimed at simplifying the use of `zig cc` for compiling C, C++, Rust, and Go programs.
Project-URL: Repository, https://github.com/jiacai2050/zigcc
Project-URL: Issues, https://github.com/jiacai2050/zigcc/issues
Author-email: Jiacai Liu <dev@liujiacai.net>
License: GPL-3.0
Keywords: compile,cross-compile,go,rust,zig
Classifier: Intended Audience :: Developers
Classifier: Intended Audience :: Information Technology
Classifier: Intended Audience :: System Administrators
Classifier: License :: OSI Approved :: GNU General Public License v3 (GPLv3)
Classifier: Operating System :: OS Independent
Classifier: Programming Language :: Python :: 3
Classifier: Programming Language :: Python :: 3 :: Only
Classifier: Programming Language :: Python :: 3.6
Classifier: Programming Language :: Python :: 3.7
Classifier: Programming Language :: Python :: 3.8
Classifier: Programming Language :: Python :: 3.9
Classifier: Programming Language :: Python :: 3.10
Classifier: Programming Language :: Python :: 3.11
Classifier: Topic :: Software Development
Requires-Python: >=3.0.0
